dap_mcp/__init__.py
dap_mcp/__main__.py
dap_mcp/config.py
dap_mcp/dap.py
dap_mcp/debugger.py
dap_mcp/factory.py
dap_mcp/render.py
dap_mcp/server.py
dap_mcp-0.1.5.dist-info/METADATA
dap_mcp-0.1.5.dist-info/WHEEL
dap_mcp-0.1.5.dist-info/entry_points.txt
dap_mcp-0.1.5.dist-info/licenses/LICENSE
dap_mcp-0.1.5.dist-info/RECORD
